gevent_requests-1.1.2.dist-info/METADATA
gevent_requests-1.1.2.dist-info/WHEEL
gevent_requests-1.1.2.dist-info/licenses/LICENSE
gevent_requests.py
gevent_requests-1.1.2.dist-info/RECORD
