Metadata-Version: 2.1
Name: gevent_requests
Version: 1.1.2
Summary: Elegant use of requests in gevent
Author-Email: belingud <im.victor@qq.com>
License: BSD
Requires-Python: >=3.8
Requires-Dist: requests
Requires-Dist: gevent>0.8
Requires-Dist: urllib3>=2.2.2
